potatoscript/potatoConfig.py
python/CodeTemplate.py
python/pyTemplate.py
python/pypiTemplate.py
python/pythonTemplate.py
CodeTemplate-1.2.5.dist-info/METADATA
CodeTemplate-1.2.5.dist-info/WHEEL
CodeTemplate-1.2.5.dist-info/top_level.txt
CodeTemplate-1.2.5.dist-info/RECORD
