Metadata-Version: 2.1
Name: CodeTemplate
Version: 1.2.5
Summary: A simple Template for create python project
Author: ks lim
Author-email: kianseng.lim@sony.com
